lmctl/__init__.py
lmctl/files.py
lmctl/journal.py
lmctl/pkg_info.json
lmctl/reference.py
lmctl/cli/__init__.py
lmctl/cli/controller.py
lmctl/cli/ctlmgmt.py
lmctl/cli/entry.py
lmctl/cli/io.py
lmctl/cli/lifecycle.py
lmctl/cli/output.py
lmctl/cli/safety_net.py
lmctl/cli/tags.py
lmctl/cli/arguments/__init__.py
lmctl/cli/arguments/environment_name.py
lmctl/cli/arguments/file_input.py
lmctl/cli/arguments/format.py
lmctl/cli/arguments/ignore_missing.py
lmctl/cli/arguments/object_group.py
lmctl/cli/arguments/output_file.py
lmctl/cli/arguments/set_param.py
lmctl/cli/arguments/tnco_secrets.py
lmctl/cli/commands/__init__.py
lmctl/cli/commands/actions.py
lmctl/cli/commands/assemblies.py
lmctl/cli/commands/assembly_components.py
lmctl/cli/commands/behaviour_assembly_configurations.py
lmctl/cli/commands/behaviour_projects.py
lmctl/cli/commands/behaviour_scenarios.py
lmctl/cli/commands/config.py
lmctl/cli/commands/deployment_location.py
lmctl/cli/commands/descriptor_templates.py
lmctl/cli/commands/descriptors.py
lmctl/cli/commands/env.py
lmctl/cli/commands/infrastructure_key.py
lmctl/cli/commands/intents.py
lmctl/cli/commands/lifecycledriver.py
lmctl/cli/commands/logdir.py
lmctl/cli/commands/login.py
lmctl/cli/commands/object_groups.py
lmctl/cli/commands/permission_type.py
lmctl/cli/commands/pkg.py
lmctl/cli/commands/processes.py
lmctl/cli/commands/project.py
lmctl/cli/commands/resource_cluster.py
lmctl/cli/commands/resource_managers.py
lmctl/cli/commands/resource_packages.py
lmctl/cli/commands/resourcedriver.py
lmctl/cli/commands/super_group.py
lmctl/cli/commands/vimdriver.py
lmctl/cli/commands/whoami.py
lmctl/cli/commands/utils/__init__.py
lmctl/cli/commands/utils/constraints.py
lmctl/cli/commands/utils/identifier.py
lmctl/cli/commands/utils/ignore_missing.py
lmctl/cli/commands/utils/obj_utils.py
lmctl/cli/commands/utils/object_groups.py
lmctl/cli/commands/utils/pass_io.py
lmctl/cli/commands/utils/tnco_builders.py
lmctl/cli/commands/utils/tnco_create_command.py
lmctl-3.6.0.dist-info/LICENSE
lmctl-3.6.0.dist-info/METADATA
lmctl-3.6.0.dist-info/WHEEL
lmctl-3.6.0.dist-info/entry_points.txt
lmctl-3.6.0.dist-info/top_level.txt
lmctl-3.6.0.dist-info/RECORD
