Metadata-Version: 2.1
Name: lmctl
Version: 3.6.0
Summary: IBM CP4NA orchestration command line tool
Home-page: https://github.com/IBM/lmctl
Author: IBM
License: UNKNOWN
Platform: UNKNOWN
Classifier: Programming Language :: Python :: 3
Classifier: License :: OSI Approved :: Apache Software License
Classifier: Operating System :: OS Independent
License-File: LICENSE
Requires-Dist: click (<9.0,>=7.1)
Requires-Dist: requests (<3.0,>=2.23)
Requires-Dist: ruamel.yaml (<1.0,>=0.16)
Requires-Dist: oyaml (<2.0,>=0.8)
Requires-Dist: tabulate (<1.0,>=0.8)
Requires-Dist: Jinja2 (<4.0,>=2.11)
Requires-Dist: PyYAML (<7.0,>=5.3.0)
Requires-Dist: pydantic (<1.10,>=1.8)
Requires-Dist: pyjwt (<3.0,>=1.5.3)
Requires-Dist: dataclasses (>=0.6) ; python_version < "3.7"
